LICENSE.txt
MANIFEST.in
README.rst
setup.cfg
setup.py
statsdmock/__init__.py
statsdmock.egg-info/PKG-INFO
statsdmock.egg-info/SOURCES.txt
statsdmock.egg-info/dependency_links.txt
statsdmock.egg-info/requires.txt
statsdmock.egg-info/top_level.txt
tests/__init__.py
tests/test_gstatsdmock.py