Metadata-Version: 1.1
Name: statsdmock
Version: 0.0.3
Summary: statsd mock server based on gevent
Home-page: http://github.com/tarzan0820/mock-statsd
Author: Salton Massally
Author-email: salton.massally@gmail.com
License: Copyright 2013 Studio Ousia
